krest/__init__.py
krest/__main__.py
krest/krest_backend.py
krest/krest_logging.py
krest/krest_qt.py
krest/krest_tui.py
krest/krest_tui.tcss
krest/translations.py
krest_utils-1.0.0.data/data/share/applications/krest_tui.tcss
krest_utils-1.0.0.dist-info/licenses/LICENSE.txt
krest_utils-1.0.0.dist-info/METADATA
krest_utils-1.0.0.dist-info/WHEEL
krest_utils-1.0.0.dist-info/entry_points.txt
krest_utils-1.0.0.dist-info/top_level.txt
krest_utils-1.0.0.dist-info/RECORD
